{
    "candles": [
        {
            "open": 145.35,
            "high": 148.405,
            "low": 144.66,
            "close": 148.16,
            "volume": 20286012,
            "datetime": 1572847200000
        },
        {
            "open": 146.74,
            "high": 148.4699,
            "low": 143.21,
            "close": 145.31,
            "volume": 13690109,
            "datetime": 1573452000000
        },
        {
            "open": 144.24,
            "high": 144.78,
            "low": 140.1018,
            "close": 143.88,
            "volume": 13765041,
            "datetime": 1574056800000
        },
        {
            "open": 144.75,
            "high": 146.65,
            "low": 143.7,
            "close": 144.73,
            "volume": 9867329,
            "datetime": 1574661600000
        },
        {
            "open": 145.2,
            "high": 146.04,
            "low": 138.5604,
            "close": 142.72,
            "volume": 13896742,
            "datetime": 1575266400000
        },
        {
            "open": 142.97,
            "high": 148.3999,
            "low": 141.75,
            "close": 145.53,
            "volume": 12794110,
            "datetime": 1575871200000
        },
        {
            "open": 147.71,
            "high": 148.3,
            "low": 144.3,
            "close": 147.57,
            "volume": 18280132,
            "datetime": 1576476000000
        },
        {
            "open": 147.68,
            "high": 148.9299,
            "low": 146.78,
            "close": 148.28,
            "volume": 6436710,
            "datetime": 1577080800000
        },
        {
            "open": 148.42,
            "high": 150.55,
            "low": 146.79,
            "close": 148.44,
            "volume": 10154131,
            "datetime": 1577685600000
        },
        {
            "open": 147.27,
            "high": 148.57,
            "low": 145.51,
            "close": 146.13,
            "volume": 12223831,
            "datetime": 1578290400000
        },
        {
            "open": 146.53,
            "high": 148.2742,
            "low": 145.2,
            "close": 147.78,
            "volume": 15143336,
            "datetime": 1578895200000
        },
        {
            "open": 147.2,
            "high": 147.87,
            "low": 139.26,
            "close": 140.38,
            "volume": 11788527,
            "datetime": 1579500000000
        },
        {
            "open": 136.9,
            "high": 137.81,
            "low": 130.54,
            "close": 131.35,
            "volume": 18953260,
            "datetime": 1580104800000
        },
        {
            "open": 131.44,
            "high": 138.33,
            "low": 129.3,
            "close": 133.37,
            "volume": 18431449,
            "datetime": 1580709600000
        },
        {
            "open": 133.04,
            "high": 140.5,
            "low": 132.78,
            "close": 137.99,
            "volume": 14068100,
            "datetime": 1581314400000
        },
        {
            "open": 137.46,
            "high": 138.89,
            "low": 135.08,
            "close": 137.21,
            "volume": 11538907,
            "datetime": 1581919200000
        },
        {
            "open": 132.53,
            "high": 133.8595,
            "low": 119.03,
            "close": 124.24,
            "volume": 29380409,
            "datetime": 1582524000000
        },
        {
            "open": 125.05,
            "high": 129.56,
            "low": 118.83,
            "close": 121.41,
            "volume": 29316568,
            "datetime": 1583128800000
        },
        {
            "open": 112.99,
            "high": 112.99,
            "low": 87.5,
            "close": 99.64,
            "volume": 42480785,
            "datetime": 1583730000000
        },
        {
            "open": 89.0,
            "high": 105.85,
            "low": 88.5,
            "close": 95.5,
            "volume": 38621332,
            "datetime": 1584334800000
        },
        {
            "open": 93.9,
            "high": 110.97,
            "low": 90.64,
            "close": 105.44,
            "volume": 32539897,
            "datetime": 1584939600000
        },
        {
            "open": 106.33,
            "high": 118.52,
            "low": 104.93,
            "close": 114.67,
            "volume": 34695561,
            "datetime": 1585544400000
        },
        {
            "open": 120.04,
            "high": 129.5998,
            "low": 118.13,
            "close": 125.03,
            "volume": 23714993,
            "datetime": 1586149200000
        },
        {
            "open": 119.95,
            "high": 120.05,
            "low": 108.86,
            "close": 116.3,
            "volume": 33397457,
            "datetime": 1586754000000
        },
        {
            "open": 114.44,
            "high": 117.07,
            "low": 108.6,
            "close": 114.04,
            "volume": 20213655,
            "datetime": 1587358800000
        },
        {
            "open": 110.85,
            "high": 120.82,
            "low": 109.73,
            "close": 110.88,
            "volume": 23211514,
            "datetime": 1587963600000
        },
        {
            "open": 110.02,
            "high": 112.2,
            "low": 106.58,
            "close": 112.11,
            "volume": 20736203,
            "datetime": 1588568400000
        },
        {
            "open": 110.16,
            "high": 110.77,
            "low": 100.22,
            "close": 107.92,
            "volume": 25583009,
            "datetime": 1589173200000
        },
        {
            "open": 112.22,
            "high": 117.48,
            "low": 111.47,
            "close": 112.47,
            "volume": 17822749,
            "datetime": 1589778000000
        },
        {
            "open": 115.98,
            "high": 124.83,
            "low": 115.98,
            "close": 120.13,
            "volume": 16670167,
            "datetime": 1590382800000
        },
        {
            "open": 119.86,
            "high": 139.37,
            "low": 117.61,
            "close": 135.12,
            "volume": 17492373,
            "datetime": 1590987600000
        },
        {
            "open": 135.32,
            "high": 139.94,
            "low": 119.35,
            "close": 123.15,
            "volume": 22439594,
            "datetime": 1591592400000
        },
        {
            "open": 118.51,
            "high": 132.44,
            "low": 118.01,
            "close": 127.46,
            "volume": 23167348,
            "datetime": 1592197200000
        },
        {
            "open": 126.36,
            "high": 127.57,
            "low": 120.8,
            "close": 122.39,
            "volume": 15479169,
            "datetime": 1592802000000
        },
        {
            "open": 123.72,
            "high": 130.34,
            "low": 123.28,
            "close": 127.72,
            "volume": 10912800,
            "datetime": 1593406800000
        },
        {
            "open": 130.13,
            "high": 130.5,
            "low": 125.115,
            "close": 128.01,
            "volume": 12145106,
            "datetime": 1594011600000
        },
        {
            "open": 129.42,
            "high": 140.99,
            "low": 128.85,
            "close": 136.9,
            "volume": 21244300,
            "datetime": 1594616400000
        },
        {
            "open": 135.76,
            "high": 138.69,
            "low": 134.255,
            "close": 137.58,
            "volume": 11512873,
            "datetime": 1595221200000
        },
        {
            "open": 137.15,
            "high": 141.0835,
            "low": 130.21,
            "close": 132.88,
            "volume": 16721155,
            "datetime": 1595826000000
        },
        {
            "open": 132.3,
            "high": 135.94,
            "low": 130.67,
            "close": 134.92,
            "volume": 12634924,
            "datetime": 1596430800000
        },
        {
            "open": 135.73,
            "high": 146.2,
            "low": 135.675,
            "close": 139.96,
            "volume": 16907465,
            "datetime": 1597035600000
        },
        {
            "open": 140.15,
            "high": 140.6007,
            "low": 135.65,
            "close": 138.43,
            "volume": 10501287,
            "datetime": 1597640400000
        },
        {
            "open": 139.76,
            "high": 145.85,
            "low": 139.08,
            "close": 143.63,
            "volume": 14478692,
            "datetime": 1598245200000
        },
        {
            "open": 143.5,
            "high": 151.2,
            "low": 140.91,
            "close": 148.18,
            "volume": 19686211,
            "datetime": 1598850000000
        },
        {
            "open": 147.0,
            "high": 155.475,
            "low": 145.72,
            "close": 153.83,
            "volume": 17744378,
            "datetime": 1599454800000
        },
        {
            "open": 154.0,
            "high": 156.25,
            "low": 148.3575,
            "close": 152.39,
            "volume": 19566591,
            "datetime": 1600059600000
        },
        {
            "open": 148.56,
            "high": 149.5,
            "low": 142.73,
            "close": 145.91,
            "volume": 13265496,
            "datetime": 1600664400000
        },
        {
            "open": 148.0,
            "high": 151.25,
            "low": 143.75,
            "close": 149.94,
            "volume": 12857620,
            "datetime": 1601269200000
        },
        {
            "open": 152.17,
            "high": 159.39,
            "low": 151.28,
            "close": 158.94,
            "volume": 13419346,
            "datetime": 1601874000000
        },
        {
            "open": 159.97,
            "high": 170.51,
            "low": 159.52,
            "close": 168.75,
            "volume": 20216531,
            "datetime": 1602478800000
        },
        {
            "open": 168.74,
            "high": 171.26,
            "low": 166.74,
            "close": 168.59,
            "volume": 13483501,
            "datetime": 1603083600000
        },
        {
            "open": 166.64,
            "high": 166.64,
            "low": 149.6301,
            "close": 157.05,
            "volume": 23252066,
            "datetime": 1603688400000
        },
        {
            "open": 159.2,
            "high": 169.0,
            "low": 155.23,
            "close": 161.29,
            "volume": 25802206,
            "datetime": 1604296800000
        },
        {
            "open": 174.03,
            "high": 176.37,
            "low": 167.47,
            "close": 171.71,
            "volume": 16121975,
            "datetime": 1604901600000
        },
        {
            "open": 175.0,
            "high": 175.3821,
            "low": 170.19,
            "close": 172.23,
            "volume": 13641137,
            "datetime": 1605506400000
        },
        {
            "open": 173.76,
            "high": 178.32,
            "low": 172.7801,
            "close": 175.08,
            "volume": 9336514,
            "datetime": 1606111200000
        },
        {
            "open": 173.61,
            "high": 183.81,
            "low": 172.28,
            "close": 182.21,
            "volume": 16054196,
            "datetime": 1606716000000
        },
        {
            "open": 180.39,
            "high": 180.7399,
            "low": 176.23,
            "close": 179.29,
            "volume": 15287449,
            "datetime": 1607320800000
        },
        {
            "open": 180.6,
            "high": 183.33,
            "low": 177.47,
            "close": 180.96,
            "volume": 14485789,
            "datetime": 1607925600000
        },
        {
            "open": 176.94,
            "high": 180.89,
            "low": 176.32,
            "close": 179.56,
            "volume": 7014324,
            "datetime": 1608530400000
        },
        {
            "open": 180.48,
            "high": 182.2293,
            "low": 175.11,
            "close": 182.02,
            "volume": 7437633,
            "datetime": 1609135200000
        },
        {
            "open": 183.0,
            "high": 197.37,
            "low": 180.25,
            "close": 194.26,
            "volume": 23531015,
            "datetime": 1609740000000
        },
        {
            "open": 191.56,
            "high": 200.1743,
            "low": 190.31,
            "close": 194.62,
            "volume": 13965775,
            "datetime": 1610344800000
        },
        {
            "open": 194.29,
            "high": 196.109,
            "low": 189.31,
            "close": 191.94,
            "volume": 8840869,
            "datetime": 1610949600000
        },
        {
            "open": 190.56,
            "high": 191.37,
            "low": 179.3401,
            "close": 182.84,
            "volume": 18425163,
            "datetime": 1611554400000
        },
        {
            "open": 185.96,
            "high": 194.33,
            "low": 182.02,
            "close": 193.0,
            "volume": 15476923,
            "datetime": 1612159200000
        },
        {
            "open": 195.0,
            "high": 199.71,
            "low": 194.39,
            "close": 197.99,
            "volume": 11856192,
            "datetime": 1612764000000
        },
        {
            "open": 199.75,
            "high": 211.46,
            "low": 198.58,
            "close": 209.91,
            "volume": 13417733,
            "datetime": 1613368800000
        },
        {
            "open": 209.63,
            "high": 226.67,
            "low": 209.335,
            "close": 215.88,
            "volume": 22402792,
            "datetime": 1613973600000
        },
        {
            "open": 219.31,
            "high": 222.58,
            "low": 208.47,
            "close": 220.16,
            "volume": 15560785,
            "datetime": 1614578400000
        },
        {
            "open": 220.97,
            "high": 229.02,
            "low": 216.14,
            "close": 229.0,
            "volume": 16103416,
            "datetime": 1615183200000
        },
        {
            "open": 228.87,
            "high": 237.78,
            "low": 224.05,
            "close": 225.29,
            "volume": 23095934,
            "datetime": 1615784400000
        },
        {
            "open": 226.62,
            "high": 229.84,
            "low": 216.0358,
            "close": 229.5,
            "volume": 16429030,
            "datetime": 1616389200000
        },
        {
            "open": 228.1,
            "high": 237.01,
            "low": 227.59,
            "close": 232.74,
            "volume": 14441724,
            "datetime": 1616994000000
        },
        {
            "open": 235.0,
            "high": 236.68,
            "low": 227.17,
            "close": 230.75,
            "volume": 12029469,
            "datetime": 1617598800000
        },
        {
            "open": 230.3,
            "high": 235.94,
            "low": 228.045,
            "close": 233.36,
            "volume": 10454239,
            "datetime": 1618203600000
        },
        {
            "open": 232.9,
            "high": 233.43,
            "low": 225.5959,
            "close": 230.11,
            "volume": 12377825,
            "datetime": 1618808400000
        },
        {
            "open": 230.57,
            "high": 235.2,
            "low": 223.2,
            "close": 228.11,
            "volume": 16185366,
            "datetime": 1619413200000
        },
        {
            "open": 230.0,
            "high": 241.89,
            "low": 225.35,
            "close": 240.99,
            "volume": 17498276,
            "datetime": 1620018000000
        },
        {
            "open": 243.5,
            "high": 245.78,
            "low": 234.5706,
            "close": 242.23,
            "volume": 14854850,
            "datetime": 1620622800000
        },
        {
            "open": 242.74,
            "high": 245.54,
            "low": 231.94,
            "close": 237.24,
            "volume": 13396541,
            "datetime": 1621227600000
        },
        {
            "open": 237.69,
            "high": 243.3684,
            "low": 236.22,
            "close": 241.08,
            "volume": 12593981,
            "datetime": 1621832400000
        },
        {
            "open": 244.01,
            "high": 246.69,
            "low": 240.7,
            "close": 244.02,
            "volume": 8585788,
            "datetime": 1622437200000
        },
        {
            "open": 244.05,
            "high": 244.33,
            "low": 220.03,
            "close": 220.7,
            "volume": 22479369,
            "datetime": 1623042000000
        },
        {
            "open": 220.07,
            "high": 221.97,
            "low": 205.5,
            "close": 208.86,
            "volume": 31577664,
            "datetime": 1623646800000
        },
        {
            "open": 211.55,
            "high": 221.93,
            "low": 211.18,
            "close": 216.31,
            "volume": 30795332,
            "datetime": 1624251600000
        },
        {
            "open": 216.45,
            "high": 219.79,
            "low": 213.5615,
            "close": 217.76,
            "volume": 14725567,
            "datetime": 1624856400000
        },
        {
            "open": 217.41,
            "high": 218.5925,
            "low": 209.93,
            "close": 217.42,
            "volume": 13943341,
            "datetime": 1625461200000
        },
        {
            "open": 216.02,
            "high": 219.05,
            "low": 207.01,
            "close": 207.95,
            "volume": 15174145,
            "datetime": 1626066000000
        },
        {
            "open": 202.27,
            "high": 211.38,
            "low": 199.23,
            "close": 209.53,
            "volume": 16967167,
            "datetime": 1626670800000
        },
        {
            "open": 209.84,
            "high": 214.51,
            "low": 203.15,
            "close": 206.75,
            "volume": 17131344,
            "datetime": 1627275600000
        },
        {
            "open": 208.0,
            "high": 210.9028,
            "low": 203.43,
            "close": 208.35,
            "volume": 15869230,
            "datetime": 1627880400000
        },
        {
            "open": 207.29,
            "high": 223.76,
            "low": 206.12,
            "close": 218.57,
            "volume": 21230511,
            "datetime": 1628485200000
        },
        {
            "open": 217.36,
            "high": 218.0,
            "low": 203.21,
            "close": 204.94,
            "volume": 17658456,
            "datetime": 1629090000000
        },
        {
            "open": 207.25,
            "high": 215.7,
            "low": 205.83,
            "close": 212.83,
            "volume": 12938415,
            "datetime": 1629694800000
        },
        {
            "open": 213.22,
            "high": 213.74,
            "low": 206.61,
            "close": 210.37,
            "volume": 14338188,
            "datetime": 1630299600000
        },
        {
            "open": 210.04,
            "high": 210.3423,
            "low": 204.77,
            "close": 205.01,
            "volume": 10575618,
            "datetime": 1630904400000
        },
        {
            "open": 207.16,
            "high": 207.86,
            "low": 199.45,
            "close": 199.75,
            "volume": 19274635,
            "datetime": 1631509200000
        },
        {
            "open": 193.06,
            "high": 197.79,
            "low": 186.98,
            "close": 196.82,
            "volume": 24342573,
            "datetime": 1632114000000
        },
        {
            "open": 197.6,
            "high": 201.99,
            "low": 191.24,
            "close": 194.33,
            "volume": 17914775,
            "datetime": 1632718800000
        },
        {
            "open": 194.74,
            "high": 196.58,
            "low": 187.8,
            "close": 195.16,
            "volume": 15940631,
            "datetime": 1633323600000
        },
        {
            "open": 196.34,
            "high": 199.45,
            "low": 187.72,
            "close": 199.02,
            "volume": 19926996,
            "datetime": 1633928400000
        },
        {
            "open": 197.38,
            "high": 205.18,
            "low": 195.545,
            "close": 200.65,
            "volume": 14076101,
            "datetime": 1634533200000
        },
        {
            "open": 201.28,
            "high": 204.5,
            "low": 195.92,
            "close": 204.09,
            "volume": 14093466,
            "datetime": 1635138000000
        }
    ],
    "symbol": "CAT",
    "empty": false
}
