{
    "candles": [
        {
            "open": 20.91,
            "high": 24.49,
            "low": 20.61,
            "close": 23.15,
            "volume": 30330420,
            "datetime": 1572238800000
        },
        {
            "open": 23.46,
            "high": 24.48,
            "low": 22.71,
            "close": 23.38,
            "volume": 18584129,
            "datetime": 1572847200000
        },
        {
            "open": 22.96,
            "high": 23.375,
            "low": 21.94,
            "close": 22.28,
            "volume": 11345575,
            "datetime": 1573452000000
        },
        {
            "open": 22.04,
            "high": 22.15,
            "low": 20.96,
            "close": 21.8,
            "volume": 12271197,
            "datetime": 1574056800000
        },
        {
            "open": 21.74,
            "high": 22.885,
            "low": 21.5,
            "close": 22.55,
            "volume": 13387296,
            "datetime": 1574661600000
        },
        {
            "open": 22.71,
            "high": 23.4,
            "low": 22.03,
            "close": 23.36,
            "volume": 20699571,
            "datetime": 1575266400000
        },
        {
            "open": 23.17,
            "high": 24.44,
            "low": 23.01,
            "close": 23.8,
            "volume": 15220957,
            "datetime": 1575871200000
        },
        {
            "open": 24.07,
            "high": 24.5,
            "low": 23.595,
            "close": 24.33,
            "volume": 16302379,
            "datetime": 1576476000000
        },
        {
            "open": 24.33,
            "high": 25.39,
            "low": 24.28,
            "close": 24.94,
            "volume": 6531329,
            "datetime": 1577080800000
        },
        {
            "open": 24.98,
            "high": 25.81,
            "low": 24.44,
            "close": 25.35,
            "volume": 10991383,
            "datetime": 1577685600000
        },
        {
            "open": 25.4,
            "high": 25.62,
            "low": 23.76,
            "close": 23.84,
            "volume": 14580659,
            "datetime": 1578290400000
        },
        {
            "open": 23.76,
            "high": 23.86,
            "low": 23.1,
            "close": 23.5,
            "volume": 13392878,
            "datetime": 1578895200000
        },
        {
            "open": 23.32,
            "high": 23.4948,
            "low": 21.58,
            "close": 21.88,
            "volume": 9249579,
            "datetime": 1579500000000
        },
        {
            "open": 21.23,
            "high": 21.535,
            "low": 20.3,
            "close": 20.61,
            "volume": 13531100,
            "datetime": 1580104800000
        },
        {
            "open": 20.63,
            "high": 24.75,
            "low": 20.5,
            "close": 24.18,
            "volume": 22423331,
            "datetime": 1580709600000
        },
        {
            "open": 23.99,
            "high": 24.21,
            "low": 22.55,
            "close": 22.89,
            "volume": 16062839,
            "datetime": 1581314400000
        },
        {
            "open": 22.59,
            "high": 23.945,
            "low": 22.345,
            "close": 23.21,
            "volume": 10351227,
            "datetime": 1581919200000
        },
        {
            "open": 22.29,
            "high": 22.4,
            "low": 18.01,
            "close": 18.71,
            "volume": 21114320,
            "datetime": 1582524000000
        },
        {
            "open": 19.03,
            "high": 20.015,
            "low": 15.2,
            "close": 15.68,
            "volume": 29047186,
            "datetime": 1583128800000
        },
        {
            "open": 11.68,
            "high": 12.58,
            "low": 8.565,
            "close": 10.18,
            "volume": 37808583,
            "datetime": 1583730000000
        },
        {
            "open": 8.51,
            "high": 11.14,
            "low": 8.0,
            "close": 10.19,
            "volume": 34207410,
            "datetime": 1584334800000
        },
        {
            "open": 10.2,
            "high": 11.81,
            "low": 9.68,
            "close": 10.06,
            "volume": 27913996,
            "datetime": 1584939600000
        },
        {
            "open": 9.67,
            "high": 10.7,
            "low": 8.89,
            "close": 9.85,
            "volume": 26709456,
            "datetime": 1585544400000
        },
        {
            "open": 10.35,
            "high": 12.74,
            "low": 10.15,
            "close": 11.6,
            "volume": 21956107,
            "datetime": 1586149200000
        },
        {
            "open": 12.04,
            "high": 12.49,
            "low": 10.41,
            "close": 11.67,
            "volume": 22688975,
            "datetime": 1586754000000
        },
        {
            "open": 10.72,
            "high": 13.1,
            "low": 10.52,
            "close": 12.02,
            "volume": 29694001,
            "datetime": 1587358800000
        },
        {
            "open": 11.79,
            "high": 13.13,
            "low": 11.44,
            "close": 11.7,
            "volume": 28358250,
            "datetime": 1587963600000
        },
        {
            "open": 11.36,
            "high": 13.325,
            "low": 11.31,
            "close": 13.19,
            "volume": 19105945,
            "datetime": 1588568400000
        },
        {
            "open": 12.87,
            "high": 13.23,
            "low": 10.79,
            "close": 11.52,
            "volume": 18091584,
            "datetime": 1589173200000
        },
        {
            "open": 12.36,
            "high": 13.0,
            "low": 11.8,
            "close": 12.09,
            "volume": 19853575,
            "datetime": 1589778000000
        },
        {
            "open": 12.74,
            "high": 13.44,
            "low": 12.07,
            "close": 12.47,
            "volume": 15035252,
            "datetime": 1590382800000
        },
        {
            "open": 12.55,
            "high": 15.3,
            "low": 12.08,
            "close": 15.03,
            "volume": 19851589,
            "datetime": 1590987600000
        },
        {
            "open": 15.72,
            "high": 16.53,
            "low": 12.185,
            "close": 12.77,
            "volume": 25444668,
            "datetime": 1591592400000
        },
        {
            "open": 12.0,
            "high": 13.54,
            "low": 11.73,
            "close": 11.74,
            "volume": 26199669,
            "datetime": 1592197200000
        },
        {
            "open": 11.66,
            "high": 12.41,
            "low": 10.95,
            "close": 12.19,
            "volume": 27108129,
            "datetime": 1592802000000
        },
        {
            "open": 12.22,
            "high": 12.52,
            "low": 11.745,
            "close": 12.1,
            "volume": 23478153,
            "datetime": 1593406800000
        },
        {
            "open": 12.43,
            "high": 12.53,
            "low": 10.735,
            "close": 11.23,
            "volume": 28485202,
            "datetime": 1594011600000
        },
        {
            "open": 11.39,
            "high": 12.03,
            "low": 10.79,
            "close": 11.36,
            "volume": 22289603,
            "datetime": 1594616400000
        },
        {
            "open": 11.36,
            "high": 12.875,
            "low": 11.225,
            "close": 12.74,
            "volume": 37716064,
            "datetime": 1595221200000
        },
        {
            "open": 12.72,
            "high": 13.27,
            "low": 11.055,
            "close": 11.51,
            "volume": 47657631,
            "datetime": 1595826000000
        },
        {
            "open": 11.51,
            "high": 12.26,
            "low": 11.4,
            "close": 11.99,
            "volume": 18843521,
            "datetime": 1596430800000
        },
        {
            "open": 12.07,
            "high": 13.3699,
            "low": 12.01,
            "close": 13.12,
            "volume": 22790542,
            "datetime": 1597035600000
        },
        {
            "open": 13.01,
            "high": 13.15,
            "low": 11.715,
            "close": 11.77,
            "volume": 18014342,
            "datetime": 1597640400000
        },
        {
            "open": 11.9,
            "high": 12.43,
            "low": 11.81,
            "close": 12.32,
            "volume": 17376124,
            "datetime": 1598245200000
        },
        {
            "open": 12.31,
            "high": 12.5,
            "low": 11.78,
            "close": 12.15,
            "volume": 18304646,
            "datetime": 1598850000000
        },
        {
            "open": 11.82,
            "high": 11.88,
            "low": 11.04,
            "close": 11.21,
            "volume": 20014360,
            "datetime": 1599454800000
        },
        {
            "open": 11.19,
            "high": 12.1,
            "low": 11.0399,
            "close": 11.74,
            "volume": 28967029,
            "datetime": 1600059600000
        },
        {
            "open": 11.27,
            "high": 11.33,
            "low": 9.5,
            "close": 9.51,
            "volume": 32394475,
            "datetime": 1600664400000
        },
        {
            "open": 9.82,
            "high": 10.1,
            "low": 8.13,
            "close": 8.7,
            "volume": 34567744,
            "datetime": 1601269200000
        },
        {
            "open": 8.89,
            "high": 9.38,
            "low": 8.59,
            "close": 9.05,
            "volume": 20794649,
            "datetime": 1601874000000
        },
        {
            "open": 9.0,
            "high": 9.1,
            "low": 8.52,
            "close": 8.6,
            "volume": 29748316,
            "datetime": 1602478800000
        },
        {
            "open": 8.72,
            "high": 9.395,
            "low": 8.62,
            "close": 9.19,
            "volume": 24276582,
            "datetime": 1603083600000
        },
        {
            "open": 9.04,
            "high": 9.2,
            "low": 7.7,
            "close": 8.4,
            "volume": 36450396,
            "datetime": 1603688400000
        },
        {
            "open": 8.59,
            "high": 9.435,
            "low": 8.33,
            "close": 9.0,
            "volume": 28916625,
            "datetime": 1604296800000
        },
        {
            "open": 10.28,
            "high": 11.905,
            "low": 10.27,
            "close": 10.98,
            "volume": 34246004,
            "datetime": 1604901600000
        },
        {
            "open": 11.68,
            "high": 12.63,
            "low": 11.48,
            "close": 12.31,
            "volume": 27770947,
            "datetime": 1605506400000
        },
        {
            "open": 12.6,
            "high": 14.15,
            "low": 12.48,
            "close": 13.15,
            "volume": 23957890,
            "datetime": 1606111200000
        },
        {
            "open": 13.03,
            "high": 14.565,
            "low": 12.195,
            "close": 14.55,
            "volume": 58165268,
            "datetime": 1606716000000
        },
        {
            "open": 14.26,
            "high": 14.995,
            "low": 13.77,
            "close": 14.32,
            "volume": 26964118,
            "datetime": 1607320800000
        },
        {
            "open": 14.63,
            "high": 14.7105,
            "low": 13.61,
            "close": 13.7,
            "volume": 27506063,
            "datetime": 1607925600000
        },
        {
            "open": 13.0,
            "high": 13.9,
            "low": 12.83,
            "close": 13.5,
            "volume": 17575372,
            "datetime": 1608530400000
        },
        {
            "open": 13.57,
            "high": 13.865,
            "low": 13.38,
            "close": 13.73,
            "volume": 14038289,
            "datetime": 1609135200000
        },
        {
            "open": 13.82,
            "high": 15.5,
            "low": 13.655,
            "close": 15.01,
            "volume": 31706729,
            "datetime": 1609740000000
        },
        {
            "open": 14.6,
            "high": 16.23,
            "low": 14.47,
            "close": 14.75,
            "volume": 22457876,
            "datetime": 1610344800000
        },
        {
            "open": 13.64,
            "high": 14.05,
            "low": 12.98,
            "close": 13.41,
            "volume": 24873146,
            "datetime": 1610949600000
        },
        {
            "open": 13.22,
            "high": 13.22,
            "low": 12.11,
            "close": 12.38,
            "volume": 27500076,
            "datetime": 1611554400000
        },
        {
            "open": 12.56,
            "high": 14.3404,
            "low": 12.31,
            "close": 13.37,
            "volume": 25201011,
            "datetime": 1612159200000
        },
        {
            "open": 13.45,
            "high": 13.97,
            "low": 13.17,
            "close": 13.94,
            "volume": 22220213,
            "datetime": 1612764000000
        },
        {
            "open": 14.36,
            "high": 14.63,
            "low": 13.69,
            "close": 14.03,
            "volume": 13113313,
            "datetime": 1613368800000
        },
        {
            "open": 14.1,
            "high": 16.0,
            "low": 13.95,
            "close": 15.1,
            "volume": 27869984,
            "datetime": 1613973600000
        },
        {
            "open": 15.39,
            "high": 17.43,
            "low": 14.83,
            "close": 17.29,
            "volume": 34423846,
            "datetime": 1614578400000
        },
        {
            "open": 17.28,
            "high": 17.5,
            "low": 15.887,
            "close": 16.7,
            "volume": 23521331,
            "datetime": 1615183200000
        },
        {
            "open": 16.73,
            "high": 16.99,
            "low": 14.62,
            "close": 14.64,
            "volume": 38713148,
            "datetime": 1615784400000
        },
        {
            "open": 14.45,
            "high": 14.62,
            "low": 12.855,
            "close": 14.03,
            "volume": 23728796,
            "datetime": 1616389200000
        },
        {
            "open": 13.83,
            "high": 14.245,
            "low": 13.48,
            "close": 14.19,
            "volume": 12323788,
            "datetime": 1616994000000
        },
        {
            "open": 14.17,
            "high": 14.17,
            "low": 12.94,
            "close": 13.09,
            "volume": 15244261,
            "datetime": 1617598800000
        },
        {
            "open": 13.2,
            "high": 14.19,
            "low": 12.81,
            "close": 13.24,
            "volume": 19999016,
            "datetime": 1618203600000
        },
        {
            "open": 13.16,
            "high": 13.43,
            "low": 12.38,
            "close": 13.29,
            "volume": 18561894,
            "datetime": 1618808400000
        },
        {
            "open": 13.37,
            "high": 15.44,
            "low": 13.16,
            "close": 14.95,
            "volume": 32526549,
            "datetime": 1619413200000
        },
        {
            "open": 15.19,
            "high": 17.29,
            "low": 15.19,
            "close": 17.25,
            "volume": 22532095,
            "datetime": 1620018000000
        },
        {
            "open": 17.4,
            "high": 17.805,
            "low": 16.28,
            "close": 17.51,
            "volume": 20598949,
            "datetime": 1620622800000
        },
        {
            "open": 17.32,
            "high": 18.02,
            "low": 15.925,
            "close": 16.17,
            "volume": 26064048,
            "datetime": 1621227600000
        },
        {
            "open": 16.26,
            "high": 16.465,
            "low": 15.84,
            "close": 16.12,
            "volume": 16645618,
            "datetime": 1621832400000
        },
        {
            "open": 16.58,
            "high": 17.829,
            "low": 16.535,
            "close": 17.66,
            "volume": 17466148,
            "datetime": 1622437200000
        },
        {
            "open": 17.7,
            "high": 17.83,
            "low": 16.7,
            "close": 16.93,
            "volume": 19380103,
            "datetime": 1623042000000
        },
        {
            "open": 17.07,
            "high": 17.66,
            "low": 15.445,
            "close": 15.61,
            "volume": 23927740,
            "datetime": 1623646800000
        },
        {
            "open": 15.77,
            "high": 16.78,
            "low": 14.98,
            "close": 15.66,
            "volume": 39685669,
            "datetime": 1624251600000
        },
        {
            "open": 15.58,
            "high": 15.925,
            "low": 14.63,
            "close": 15.52,
            "volume": 22041952,
            "datetime": 1624856400000
        },
        {
            "open": 15.54,
            "high": 15.54,
            "low": 13.811,
            "close": 15.03,
            "volume": 15951771,
            "datetime": 1625461200000
        },
        {
            "open": 14.73,
            "high": 15.33,
            "low": 13.48,
            "close": 13.62,
            "volume": 21395021,
            "datetime": 1626066000000
        },
        {
            "open": 13.32,
            "high": 14.235,
            "low": 12.95,
            "close": 13.57,
            "volume": 21273028,
            "datetime": 1626670800000
        },
        {
            "open": 13.65,
            "high": 14.45,
            "low": 13.59,
            "close": 13.81,
            "volume": 26459683,
            "datetime": 1627275600000
        },
        {
            "open": 13.81,
            "high": 14.56,
            "low": 12.88,
            "close": 13.45,
            "volume": 20903525,
            "datetime": 1627880400000
        },
        {
            "open": 13.05,
            "high": 14.005,
            "low": 12.785,
            "close": 13.22,
            "volume": 18909520,
            "datetime": 1628485200000
        },
        {
            "open": 12.94,
            "high": 13.09,
            "low": 11.841,
            "close": 12.19,
            "volume": 25185309,
            "datetime": 1629090000000
        },
        {
            "open": 12.6,
            "high": 13.78,
            "low": 12.48,
            "close": 13.69,
            "volume": 15070464,
            "datetime": 1629694800000
        },
        {
            "open": 13.93,
            "high": 13.98,
            "low": 12.9,
            "close": 12.95,
            "volume": 19299623,
            "datetime": 1630299600000
        },
        {
            "open": 12.86,
            "high": 13.4,
            "low": 12.49,
            "close": 13.09,
            "volume": 20519510,
            "datetime": 1630904400000
        },
        {
            "open": 13.18,
            "high": 14.38,
            "low": 13.18,
            "close": 13.39,
            "volume": 113476047,
            "datetime": 1631509200000
        },
        {
            "open": 12.91,
            "high": 13.26,
            "low": 12.25,
            "close": 12.96,
            "volume": 24710497,
            "datetime": 1632114000000
        },
        {
            "open": 13.34,
            "high": 13.82,
            "low": 13.07,
            "close": 13.48,
            "volume": 21648992,
            "datetime": 1632718800000
        },
        {
            "open": 13.72,
            "high": 14.685,
            "low": 13.47,
            "close": 14.62,
            "volume": 23845052,
            "datetime": 1633323600000
        },
        {
            "open": 14.82,
            "high": 15.12,
            "low": 14.19,
            "close": 14.99,
            "volume": 15095954,
            "datetime": 1633928400000
        },
        {
            "open": 14.93,
            "high": 15.5,
            "low": 14.55,
            "close": 14.89,
            "volume": 18902155,
            "datetime": 1634533200000
        }
    ],
    "symbol": "NOV",
    "empty": false
}
